{"cameraMode":{"drawMode":0,"name":"Shaded","section":"Shading Mode"},"sceneLighting":false,"audioPlay":false,"sceneViewState":{"showFog":false,"showMaterialUpdate":false,"showSkybox":false,"showFlares":false,"showImageEffects":false,"showParticleSystems":false},"in2DMode":false,"pivot":{"x":0.0,"y":12.018126487731934,"z":-9.5367431640625e-7},"rotation":{"x":0.03715277463197708,"y":0.07519695162773133,"z":-0.0061091044917702679,"w":0.9968775510787964},"size":22.88614273071289,"orthographic":false}